{"is_source_file": true, "format": "JavaScript", "description": "This file is the entry point for a React application, initializing the React DOM root and rendering the main App component within StrictMode.", "external_files": ["react", "react-dom/client", "./index.css", "./App"], "external_methods": ["ReactDOM.createRoot", "ReactDOM.render"], "published": ["React", "ReactDOM"], "classes": [], "methods": [{"name": "ReactDOM.createRoot", "description": "Creates a React root for the React application rendering."}], "calls": ["ReactDOM.createRoot", "root.render"], "search-terms": ["ReactDOM", "index.js", "React entry point", "React root", "render"], "state": 2, "file_id": 3, "knowledge_revision": 20, "git_revision": "9eef36b1341e07af52538c189a3b5bebf2beb49c", "ctags": [{"_type": "tag", "name": "root", "path": "/home/kavia/workspace/code-generation/react-figma-inspired-frontend-209913-209922/react_frontend/src/index.js", "pattern": "/^const root = ReactDOM.createRoot(document.getElementById('root'));$/", "language": "JavaScript", "kind": "constant"}], "hash": "9fc5841375336fc175b49f8767a11383", "format-version": 4, "code-base-name": "react_frontend", "filename": "react_frontend/src/index.js", "revision_history": [{"20": "9eef36b1341e07af52538c189a3b5bebf2beb49c"}]}